smtp_checker/__init__.py
smtp_checker/cli.py
smtp_checker/smtp_utils.py
smtp_checker_cli-0.1.0.dist-info/licenses/LICENSE
smtp_checker_cli-0.1.0.dist-info/METADATA
smtp_checker_cli-0.1.0.dist-info/WHEEL
smtp_checker_cli-0.1.0.dist-info/entry_points.txt
smtp_checker_cli-0.1.0.dist-info/top_level.txt
smtp_checker_cli-0.1.0.dist-info/RECORD
