Metadata-Version: 2.4
Name: smtp-checker-cli
Version: 0.1.0
Summary: SMTP Checker CLI tool
Author: Nama Kamu
License: MIT
Classifier: Programming Language :: Python :: 3
Classifier: License :: OSI Approved :: MIT License
Requires-Python: >=3.7
License-File: LICENSE
Dynamic: author
Dynamic: classifier
Dynamic: license
Dynamic: license-file
Dynamic: requires-python
